check/__init__.py
check/check.py
check_cuda-0.0.3.dist-info/LICENSE
check_cuda-0.0.3.dist-info/METADATA
check_cuda-0.0.3.dist-info/WHEEL
check_cuda-0.0.3.dist-info/top_level.txt
check_cuda-0.0.3.dist-info/RECORD
