Metadata-Version: 2.1
Name: check-cuda
Version: 0.0.3
Summary: 检查CUDA版本
Home-page: https://github.com/wangruihua/checkcuda
Author: wangruihua
Author-email: wangruihua <wangruihua@163.com>
Project-URL: Homepage, https://github.com/pypa/sampleproject
Project-URL: Issues, https://github.com/pypa/sampleproject/issues
Classifier: Programming Language :: Python :: 3
Classifier: License :: OSI Approved :: MIT License
Classifier: Operating System :: OS Independent
Requires-Python: >=3.6
License-File: LICENSE
